scale_gp_beta/__init__.py
scale_gp_beta/_base_client.py
scale_gp_beta/_client.py
scale_gp_beta/_compat.py
scale_gp_beta/_constants.py
scale_gp_beta/_exceptions.py
scale_gp_beta/_files.py
scale_gp_beta/_models.py
scale_gp_beta/_qs.py
scale_gp_beta/_resource.py
scale_gp_beta/_response.py
scale_gp_beta/_streaming.py
scale_gp_beta/_types.py
scale_gp_beta/_version.py
scale_gp_beta/pagination.py
scale_gp_beta/py.typed
scale_gp_beta/_utils/__init__.py
scale_gp_beta/_utils/_compat.py
scale_gp_beta/_utils/_datetime_parse.py
scale_gp_beta/_utils/_logs.py
scale_gp_beta/_utils/_proxy.py
scale_gp_beta/_utils/_reflection.py
scale_gp_beta/_utils/_resources_proxy.py
scale_gp_beta/_utils/_streams.py
scale_gp_beta/_utils/_sync.py
scale_gp_beta/_utils/_transform.py
scale_gp_beta/_utils/_typing.py
scale_gp_beta/_utils/_utils.py
scale_gp_beta/lib/.keep
scale_gp_beta/lib/CONTRIBUTING.MD
scale_gp_beta/lib/tracing/__init__.py
scale_gp_beta/lib/tracing/exceptions.py
scale_gp_beta/lib/tracing/scope.py
scale_gp_beta/lib/tracing/span.py
scale_gp_beta/lib/tracing/trace.py
scale_gp_beta/lib/tracing/trace_exporter.py
scale_gp_beta/lib/tracing/trace_queue_manager.py
scale_gp_beta/lib/tracing/tracing.py
scale_gp_beta/lib/tracing/types.py
scale_gp_beta/lib/tracing/util.py
scale_gp_beta/lib/tracing/integrations/__init__.py
scale_gp_beta/lib/tracing/integrations/openai/__init__.py
scale_gp_beta/lib/tracing/integrations/openai/openai_span_type_map.py
scale_gp_beta/lib/tracing/integrations/openai/openai_tracing_sgp_processor.py
scale_gp_beta/lib/tracing/integrations/openai/utils.py
scale_gp_beta/resources/__init__.py
scale_gp_beta/resources/build.py
scale_gp_beta/resources/completions.py
scale_gp_beta/resources/credentials.py
scale_gp_beta/resources/dataset_items.py
scale_gp_beta/resources/datasets.py
scale_gp_beta/resources/evaluation_items.py
scale_gp_beta/resources/evaluations.py
scale_gp_beta/resources/inference.py
scale_gp_beta/resources/models.py
scale_gp_beta/resources/questions.py
scale_gp_beta-0.1.0a42.dist-info/METADATA
scale_gp_beta-0.1.0a42.dist-info/WHEEL
scale_gp_beta-0.1.0a42.dist-info/licenses/LICENSE
scale_gp_beta-0.1.0a42.dist-info/RECORD
